ffmpeg_gui/__init__.py
ffmpeg_gui/__main__.py
ffmpeg_gui/ffmpeg_wrapper.py
ffmpeg_gui/gui.py
ffmpeg_gui-0.0.1.dist-info/LICENSE
ffmpeg_gui-0.0.1.dist-info/METADATA
ffmpeg_gui-0.0.1.dist-info/WHEEL
ffmpeg_gui-0.0.1.dist-info/entry_points.txt
ffmpeg_gui-0.0.1.dist-info/top_level.txt
ffmpeg_gui-0.0.1.dist-info/RECORD
